NURBSDiff/__init__.py
NURBSDiff/curve_eval.py
NURBSDiff/curve_eval_cpp.cpython-311-x86_64-linux-gnu.so
NURBSDiff/curve_eval_cuda.cpython-311-x86_64-linux-gnu.so
NURBSDiff/nurbs_eval.py
NURBSDiff/surf_eval.py
NURBSDiff/surf_eval_cpp.cpython-311-x86_64-linux-gnu.so
NURBSDiff/surf_eval_cuda.cpython-311-x86_64-linux-gnu.so
NURBSDiff/utils.py
NURBSDiff/csrc/curve_eval.cpp
NURBSDiff/csrc/curve_eval_cuda.cpp
NURBSDiff/csrc/curve_eval_cuda_kernel.cu
NURBSDiff/csrc/surf_eval.cpp
NURBSDiff/csrc/surf_eval_cuda.cpp
NURBSDiff/csrc/surf_eval_cuda_kernel.cu
NURBSDiff/csrc/utils.cpp
NURBSDiff/csrc/utils.h
pipableNURBSDiff-0.0.5.dist-info/LICENSE
pipableNURBSDiff-0.0.5.dist-info/METADATA
pipableNURBSDiff-0.0.5.dist-info/WHEEL
pipableNURBSDiff-0.0.5.dist-info/top_level.txt
pipableNURBSDiff-0.0.5.dist-info/RECORD
