Metadata-Version: 2.1
Name: pipableNURBSDiff
Version: 0.0.5
Summary: NURBS-diff is a differentiable layer that can be run as a standalone layer for CAD applications like curve fitting, surface fitting, surface offseting, and other applications that rely on Non-uniform rational B-splines (NURBS) for representation..
Author: N/A
License: BSD 3-Clause License
Project-URL: Homepage, https://github.com/orthly/NURBSDiff
Project-URL: Bug Reports, https://github.com/orthly/NURBSDiff
Project-URL: Source, https://github.com/orthly/NURBSDiff
Classifier: Development Status :: 5 - Production/Stable
Classifier: Intended Audience :: Developers
Classifier: License :: OSI Approved :: BSD License
Classifier: Programming Language :: Python :: 3
Classifier: Programming Language :: Python :: 3.10
Classifier: Programming Language :: Python :: 3.11
Classifier: Programming Language :: Python :: 3 :: Only
Requires-Python: <3.12,>=3.8
License-File: LICENSE
